baidu-map/python/src/mcp_server_baidu_maps/__init__.py
baidu-map/python/src/mcp_server_baidu_maps/__main__.py
baidu-map/python/src/mcp_server_baidu_maps/map.py
iflow_mcp_mcp_server_baidu_maps-0.2.4.dist-info/licenses/LICENSE
mcp_server_baidu_maps/__init__.py
mcp_server_baidu_maps/__main__.py
mcp_server_baidu_maps/map.py
iflow_mcp_mcp_server_baidu_maps-0.2.4.dist-info/METADATA
iflow_mcp_mcp_server_baidu_maps-0.2.4.dist-info/WHEEL
iflow_mcp_mcp_server_baidu_maps-0.2.4.dist-info/entry_points.txt
iflow_mcp_mcp_server_baidu_maps-0.2.4.dist-info/top_level.txt
iflow_mcp_mcp_server_baidu_maps-0.2.4.dist-info/RECORD
