Metadata-Version: 2.4
Name: iflow-mcp_mcp-server-baidu-maps
Version: 0.2.4
Summary: MCP Server Baidu Maps
Author: baidu-maps
Maintainer-email: Pineapple274 <yuyangyang3838@gmail.com>
License: MIT
Keywords: http,mcp,map,baidu
Requires-Python: >=3.11
License-File: LICENSE
Requires-Dist: mcp[cli]>=1.9.0
Dynamic: license-file
